{"type": "FeatureCollection", "features": [{"type": "Feature", "geometry": {"type": "Point", "coordinates": [-15.151, 51.606]}, "properties": {"ptf_id": 1015281, "ptf_ref": "LRYQE3U", "category": "ship_based_meteorological_sot", "ptf_model": "DIS - Fixed manual deck launcher", "country_name": "EUMETNET"}}, {"type": "Feature", "geometry": {"type": "Point", "coordinates": [-57.831, 45.479]}, "properties": {"ptf_id": 1015282, "ptf_ref": "JNKN7JF", "category": "ship_based_meteorological_sot", "ptf_model": "DIS - Fixed manual deck launcher", "country_name": "EUMETNET"}}, {"type": "Feature", "geometry": {"type": "Point", "coordinates": [-56.25, 45.805]}, "properties": {"ptf_id": 1015283, "ptf_ref": "7JUNA4N", "category": "ship_based_meteorological_sot", "ptf_model": "DIS - Fixed manual deck launcher", "country_name": "EUMETNET"}}, {"type": "Feature", "geometry": {"type": "Point", "coordinates": [-22.991, 54.757]}, "properties": {"ptf_id": 1015284, "ptf_ref": "YLV96WM", "category": "ship_based_meteorological_sot", "ptf_model": "DIS - Fixed manual deck launcher", "country_name": "EUMETNET"}}, {"type": "Feature", "geometry": {"type": "Point", "coordinates": [-24.876, 48.034]}, "properties": {"ptf_id": 1015285, "ptf_ref": "KMPLHPW", "category": "ship_based_meteorological_sot", "ptf_model": "DIS - Fixed manual deck launcher", "country_name": "EUMETNET"}}, {"type": "Feature", "geometry": {"type": "Point", "coordinates": [1.519, 72.395]}, "properties": {"ptf_id": 1015286, "ptf_ref": "WDK38HS", "category": "ship_based_meteorological_sot", "ptf_model": "INT - Semi automatic 10ft container launcher", "country_name": "EUMETNET"}}, {"type": "Feature", "geometry": {"type": "Point", "coordinates": [1.835, 67.386]}, "properties": {"ptf_id": 1015287, "ptf_ref": "FPUW5GN", "category": "ship_based_meteorological_sot", "ptf_model": "INT - Semi automatic 10ft container launcher", "country_name": "EUMETNET"}}, {"type": "Feature", "geometry": {"type": "Point", "coordinates": [-16.384, 30.191]}, "properties": {"ptf_id": 1015288, "ptf_ref": "ZVQEQCM", "category": "ship_based_meteorological_sot", "ptf_model": "INT - Semi automatic 20ft container launcher", "country_name": "EUMETNET"}}, {"type": "Feature", "geometry": {"type": "Point", "coordinates": [-56.585, 19.694]}, "properties": {"ptf_id": 1133915, "ptf_ref": "UXK5JTU", "category": "ship_based_meteorological_sot", "ptf_model": "DIS - Fixed manual deck launcher", "country_name": "EUMETNET"}}, {"type": "Feature", "geometry": {"type": "Point", "coordinates": [-54.433, 23.427]}, "properties": {"ptf_id": 1133916, "ptf_ref": "KJJF9XN", "category": "ship_based_meteorological_sot", "ptf_model": "DIS - Fixed manual deck launcher", "country_name": "EUMETNET"}}, {"type": "Feature", "geometry": {"type": "Point", "coordinates": [-51.21, 62.97]}, "properties": {"ptf_id": 1141996, "ptf_ref": "9ZT9MRK", "category": "ship_based_meteorological_sot", "ptf_model": "DIS - Free hand launches", "country_name": "EUMETNET"}}, {"type": "Feature", "geometry": {"type": "Point", "coordinates": [127.8, 29]}, "properties": {"ptf_id": 1146190, "ptf_ref": "NSWRJMD", "category": "ship_based_meteorological_sot", "ptf_model": "DIS - Semi automatic 10ft container launcher", "country_name": "JAPAN"}}, {"type": "Feature", "geometry": {"type": "Point", "coordinates": [-29.85, 63.244]}, "properties": {"ptf_id": 1149487, "ptf_ref": "ATGU3FT", "category": "ship_based_meteorological_sot", "ptf_model": "DIS - Free hand launches", "country_name": "EUMETNET"}}, {"type": "Feature", "geometry": {"type": "Point", "coordinates": [8.9, -32.8]}, "properties": {"ptf_id": 1016940, "ptf_ref": "PGFVDZX", "category": "ship_based_meteorological_sot", "ptf_model": "OT ASAP", "country_name": "SOUTH AFRICA"}}]}
